cmd.py
dj_database_waiter/__init__.py
dj_database_waiter/cmd.py
dj_database_waiter-0.0.2.dist-info/DESCRIPTION.rst
dj_database_waiter-0.0.2.dist-info/METADATA
dj_database_waiter-0.0.2.dist-info/RECORD
dj_database_waiter-0.0.2.dist-info/WHEEL
dj_database_waiter-0.0.2.dist-info/entry_points.txt
dj_database_waiter-0.0.2.dist-info/metadata.json
dj_database_waiter-0.0.2.dist-info/top_level.txt
